example.py
tcurses/__init__.py
tcurses/__init__.pyi
tcurses-0.0.9.dist-info/LICENSE
tcurses-0.0.9.dist-info/METADATA
tcurses-0.0.9.dist-info/WHEEL
tcurses-0.0.9.dist-info/top_level.txt
tcurses-0.0.9.dist-info/RECORD
